{
  "oi": 329313,
  "ps": [
    {
      "d": "2023-06-04",
      "ix": "∑{e}[A348268(n), #]",
      "mt": 87,
      "px": [
        "n",
        "A348268",
        "#",
        "∑{e}"
      ]
    },
    {
      "d": "2021-11-01",
      "ix": "A001222(A348268(n))",
      "mt": 87,
      "px": [
        "n",
        "A348268",
        "A001222"
      ]
    },
    {
      "d": "2022-10-07",
      "ix": "A211100(A145341(n+1))-1",
      "mt": 87,
      "px": [
        "n",
        "1",
        "+",
        "A145341",
        "A211100",
        "1",
        "sub"
      ]
    },
    {
      "d": "2023-07-31",
      "ix": "A211100(A030101(2*n+1))-1",
      "mt": 87,
      "px": [
        "2",
        "n",
        "*",
        "1",
        "+",
        "A030101",
        "A211100",
        "1",
        "sub"
      ]
    },
    {
      "d": "2023-06-10",
      "ix": "A211100(A057889(2*n+1))-1",
      "mt": 87,
      "px": [
        "2",
        "n",
        "*",
        "1",
        "+",
        "A057889",
        "A211100",
        "1",
        "sub"
      ]
    }
  ]
}