{
  "oi": 241063,
  "ps": [
    {
      "d": "2023-04-04",
      "ix": "A332111(n+1)%d(A332077(n+1))",
      "mt": 17,
      "px": [
        "n",
        "1",
        "+",
        "A332111",
        "n",
        "1",
        "+",
        "A332077",
        "d",
        "%"
      ]
    },
    {
      "d": "2023-04-11",
      "ix": "∑[A281555(2*(n+2))]%A124156(n+1)",
      "mt": 17,
      "px": [
        "2",
        "n",
        "2",
        "+",
        "*",
        "A281555",
        "∑",
        "n",
        "1",
        "+",
        "A124156",
        "%"
      ]
    },
    {
      "d": "2023-03-15",
      "ix": "A162641(A136467(n))",
      "mt": 16,
      "px": [
        "n",
        "A136467",
        "A162641"
      ]
    },
    {
      "d": "2021-11-25",
      "ix": "A073484(A038505(n)+1)",
      "mt": 16,
      "px": [
        "n",
        "A038505",
        "1",
        "+",
        "A073484"
      ]
    },
    {
      "d": "2023-03-16",
      "ix": "A084114(A054253(n+1))",
      "mt": 16,
      "px": [
        "n",
        "1",
        "+",
        "A054253",
        "A084114"
      ]
    }
  ]
}