{
  "oi": 291708,
  "ps": [
    {
      "d": "2022-05-22",
      "ix": "ceil(n/2-A062602(n+1))",
      "mt": 10000,
      "px": [
        "n",
        "2",
        "/",
        "n",
        "1",
        "+",
        "A062602",
        "sub",
        "ceil"
      ]
    },
    {
      "d": "2021-11-24",
      "ix": "A110654(n)-A062602(n+1)",
      "mt": 10000,
      "px": [
        "n",
        "A110654",
        "n",
        "1",
        "+",
        "A062602",
        "sub"
      ]
    },
    {
      "d": "2021-12-21",
      "ix": "abs(A001057(n))-A062602(n+1)",
      "mt": 10000,
      "px": [
        "n",
        "A001057",
        "abs",
        "n",
        "1",
        "+",
        "A062602",
        "sub"
      ]
    },
    {
      "d": "2022-07-21",
      "ix": "abs(A130472(n))-A062602(n+1)",
      "mt": 10000,
      "px": [
        "n",
        "A130472",
        "abs",
        "n",
        "1",
        "+",
        "A062602",
        "sub"
      ]
    },
    {
      "d": "2021-12-14",
      "ix": "∑[A000035(n)]-A062602(n+1)",
      "mt": 10000,
      "px": [
        "n",
        "A000035",
        "∑",
        "n",
        "1",
        "+",
        "A062602",
        "sub"
      ]
    },
    {
      "d": "2021-12-21",
      "ix": "Δ[A002620(n)]-A062602(n+1)",
      "mt": 10000,
      "px": [
        "n",
        "A002620",
        "Δ",
        "n",
        "1",
        "+",
        "A062602",
        "sub"
      ]
    },
    {
      "d": "2021-11-24",
      "ix": "A062610(n+1)+A061358(n+1)",
      "mt": 10000,
      "px": [
        "n",
        "1",
        "+",
        "A062610",
        "n",
        "1",
        "+",
        "A061358",
        "+"
      ]
    },
    {
      "d": "2024-09-18",
      "ix": "n-(A062602(n+1)+A004526(n))",
      "mt": 10000,
      "px": [
        "n",
        "n",
        "1",
        "+",
        "A062602",
        "n",
        "A004526",
        "+",
        "sub"
      ]
    },
    {
      "d": "2022-06-09",
      "ix": "∑[val(A020639(n+1), 2)]-A062602(n+1)",
      "mt": 10000,
      "px": [
        "n",
        "1",
        "+",
        "A020639",
        "2",
        "val",
        "∑",
        "n",
        "1",
        "+",
        "A062602",
        "sub"
      ]
    },
    {
      "d": "2022-06-06",
      "ix": "log2(A060546(n))-A062602(n+1)",
      "mt": 665,
      "px": [
        "n",
        "A060546",
        "log2",
        "n",
        "1",
        "+",
        "A062602",
        "sub"
      ]
    }
  ]
}