{
  "oi": 307182,
  "ps": [
    {
      "d": "2021-12-11",
      "ix": "floor((n/2-floor((n/2)²))²)",
      "mt": 10000,
      "px": [
        "n",
        "2",
        "/",
        "n",
        "2",
        "/",
        "²",
        "floor",
        "sub",
        "²",
        "floor"
      ]
    },
    {
      "d": "2022-04-11",
      "ix": "(round((n/2)²)-(2*n)%(n+1))*round((n/2)²)",
      "mt": 10000,
      "px": [
        "n",
        "2",
        "/",
        "²",
        "round",
        "2",
        "n",
        "*",
        "n",
        "1",
        "+",
        "%",
        "sub",
        "n",
        "2",
        "/",
        "²",
        "round",
        "*"
      ]
    },
    {
      "d": "2021-11-01",
      "ix": "∑[4*A028724(n)]",
      "mt": 10000,
      "px": [
        "4",
        "n",
        "A028724",
        "*",
        "∑"
      ]
    },
    {
      "d": "2022-05-08",
      "ix": "round((n/2-A002620(n))²)",
      "mt": 10000,
      "px": [
        "n",
        "2",
        "/",
        "n",
        "A002620",
        "sub",
        "²",
        "round"
      ]
    },
    {
      "d": "2021-11-24",
      "ix": "A028724(n)*A131055(n+1)",
      "mt": 10000,
      "px": [
        "n",
        "A028724",
        "n",
        "1",
        "+",
        "A131055",
        "*"
      ]
    },
    {
      "d": "2021-12-05",
      "ix": "(A033638(n)-n)*A002620(n)",
      "mt": 10000,
      "px": [
        "n",
        "A033638",
        "n",
        "sub",
        "n",
        "A002620",
        "*"
      ]
    },
    {
      "d": "2022-04-29",
      "ix": "A002620(abs(2-n))*A002620(n)",
      "mt": 10000,
      "px": [
        "2",
        "n",
        "sub",
        "abs",
        "A002620",
        "n",
        "A002620",
        "*"
      ]
    },
    {
      "d": "2022-10-07",
      "ix": "(A033638(n)-n)*∑[A004526(n)]",
      "mt": 10000,
      "px": [
        "n",
        "A033638",
        "n",
        "sub",
        "n",
        "A004526",
        "∑",
        "*"
      ]
    },
    {
      "d": "2021-10-01",
      "ix": "(sqrt(A030179(n))+1-n)*sqrt(A030179(n))",
      "mt": 10000,
      "px": [
        "n",
        "A030179",
        "sqrt",
        "1",
        "+",
        "n",
        "sub",
        "n",
        "A030179",
        "sqrt",
        "*"
      ]
    },
    {
      "d": "2022-05-05",
      "ix": "(A002620(n)-A023443(n))*A002620(n)",
      "mt": 10000,
      "px": [
        "n",
        "A002620",
        "n",
        "A023443",
        "sub",
        "n",
        "A002620",
        "*"
      ]
    },
    {
      "d": "2025-03-23",
      "ix": "4*A000241(n+1)",
      "mt": 9999,
      "px": [
        "4",
        "n",
        "1",
        "+",
        "A000241",
        "*"
      ]
    },
    {
      "d": "2022-05-06",
      "ix": "2*A028724(n)*A004526(n+1)",
      "mt": 9999,
      "px": [
        "2",
        "n",
        "A028724",
        "*",
        "n",
        "1",
        "+",
        "A004526",
        "*"
      ]
    },
    {
      "d": "2022-05-09",
      "ix": "(A084265(n+1)-A000124(n+1))*A028724(n)",
      "mt": 9999,
      "px": [
        "n",
        "1",
        "+",
        "A084265",
        "n",
        "1",
        "+",
        "A000124",
        "sub",
        "n",
        "A028724",
        "*"
      ]
    },
    {
      "d": "2022-05-06",
      "ix": "(A008797(2*n)-2*n)*A008797(2*n+1)",
      "mt": 5000,
      "px": [
        "2",
        "n",
        "*",
        "A008797",
        "2",
        "n",
        "*",
        "sub",
        "2",
        "n",
        "*",
        "1",
        "+",
        "A008797",
        "*"
      ]
    },
    {
      "d": "2022-06-26",
      "ix": "A002620(n)*A265409(A002620(n+2))",
      "mt": 199,
      "px": [
        "n",
        "A002620",
        "n",
        "2",
        "+",
        "A002620",
        "A265409",
        "*"
      ]
    },
    {
      "d": "2021-11-24",
      "ix": "A182568(A261243(n+1))",
      "mt": 143,
      "px": [
        "n",
        "1",
        "+",
        "A261243",
        "A182568"
      ]
    },
    {
      "d": "2022-05-05",
      "ix": "A182568(A007590(n)+2-n)",
      "mt": 143,
      "px": [
        "n",
        "A007590",
        "2",
        "n",
        "sub",
        "+",
        "A182568"
      ]
    },
    {
      "d": "2022-05-05",
      "ix": "A182568(2-(n-A007590(n)))",
      "mt": 143,
      "px": [
        "2",
        "n",
        "n",
        "A007590",
        "sub",
        "sub",
        "A182568"
      ]
    },
    {
      "d": "2022-05-09",
      "ix": "A002620(A004277(A002620(n))-n)",
      "mt": 143,
      "px": [
        "n",
        "A002620",
        "A004277",
        "n",
        "sub",
        "A002620"
      ]
    },
    {
      "d": "2025-03-23",
      "ix": "A298368(A054254(n+1))",
      "mt": 141,
      "px": [
        "n",
        "1",
        "+",
        "A054254",
        "A298368"
      ]
    }
  ]
}