{
  "oi": 247610,
  "ps": [
    {
      "d": "2025-04-12",
      "ix": "(20+508*n-925*n²+820*n^3-245*n^4+42*n^5)/20",
      "mt": 10000,
      "px": [
        "20",
        "508",
        "n",
        "*",
        "+",
        "925",
        "n",
        "²",
        "*",
        "sub",
        "820",
        "n",
        "3",
        "^",
        "*",
        "+",
        "245",
        "n",
        "4",
        "^",
        "*",
        "sub",
        "42",
        "n",
        "5",
        "^",
        "*",
        "+",
        "20",
        "/"
      ],
      "s": "oeis",
      "tags": [
        "proven"
      ]
    }
  ]
}