{
  "oi": 96220,
  "ps": [
    {
      "d": "2024-12-13",
      "ix": "∑[∑[A054242(lcm(2, n)+n%2)]]",
      "mt": 9,
      "px": [
        "2",
        "n",
        "lcm",
        "n",
        "2",
        "%",
        "+",
        "A054242",
        "∑",
        "∑"
      ]
    },
    {
      "d": "2023-09-02",
      "ix": "∑[round(comp[A295027(n+1)]²/8)]",
      "mt": 9,
      "px": [
        "n",
        "1",
        "+",
        "A295027",
        "comp",
        "²",
        "8",
        "/",
        "round",
        "∑"
      ]
    },
    {
      "d": "2023-04-07",
      "ix": "∑[∑[∏{p}[A353161(2*n+3), #]]]",
      "mt": 9,
      "px": [
        "2",
        "n",
        "*",
        "3",
        "+",
        "A353161",
        "#",
        "∏{p}",
        "∑",
        "∑"
      ]
    },
    {
      "d": "2022-08-06",
      "ix": "∑[∑[A353147(n+1)%(n+1)]+1]",
      "mt": 9,
      "px": [
        "n",
        "1",
        "+",
        "A353147",
        "n",
        "1",
        "+",
        "%",
        "∑",
        "1",
        "+",
        "∑"
      ]
    },
    {
      "d": "2022-10-14",
      "ix": "∑[record[(n+1)%(A109671(2*n+1)+1)]]",
      "mt": 9,
      "px": [
        "n",
        "1",
        "+",
        "2",
        "n",
        "*",
        "1",
        "+",
        "A109671",
        "1",
        "+",
        "%",
        "record",
        "∑"
      ]
    }
  ]
}