{
  "oi": 83982,
  "ps": [
    {
      "d": "2022-06-19",
      "ix": "p?[A085054(A037124(n+1))]",
      "mt": 11,
      "px": [
        "n",
        "1",
        "+",
        "A037124",
        "A085054",
        "p?"
      ]
    },
    {
      "d": "2022-10-11",
      "ix": "p?[gcd(A056967(n+1), A085054(n+1))]",
      "mt": 11,
      "px": [
        "n",
        "1",
        "+",
        "A056967",
        "n",
        "1",
        "+",
        "A085054",
        "gcd",
        "p?"
      ]
    },
    {
      "d": "2022-07-04",
      "ix": "A085054(C(A037124(n+1), A004086(n)))",
      "mt": 11,
      "px": [
        "n",
        "1",
        "+",
        "A037124",
        "n",
        "A004086",
        "C",
        "A085054"
      ]
    },
    {
      "d": "2024-09-16",
      "ix": "A085054(A062399(n+1))",
      "mt": 10,
      "px": [
        "n",
        "1",
        "+",
        "A062399",
        "A085054"
      ]
    },
    {
      "d": "2024-09-18",
      "ix": "A085054(A087051(n)+1)",
      "mt": 10,
      "px": [
        "n",
        "A087051",
        "1",
        "+",
        "A085054"
      ]
    }
  ]
}