{
  "oi": 151414,
  "ps": [
    {
      "d": "2026-04-17",
      "ix": "A246277(A064665(3*a(n-1)-2*a(n-2)))",
      "mt": 8,
      "px": [
        "1",
        "0",
        "1",
        "2",
        "6",
        "14",
        "3",
        "n",
        "1",
        "sub",
        "a",
        "*",
        "2",
        "n",
        "2",
        "sub",
        "a",
        "*",
        "sub",
        "A064665",
        "A246277"
      ]
    },
    {
      "d": "2023-07-30",
      "ix": "A033109(A040059(n)+A006516(n))",
      "mt": 8,
      "px": [
        "n",
        "A040059",
        "n",
        "A006516",
        "+",
        "A033109"
      ]
    },
    {
      "d": "2023-07-09",
      "ix": "A057428(n)+A055086(A060656(n))",
      "mt": 8,
      "px": [
        "n",
        "A057428",
        "n",
        "A060656",
        "A055086",
        "+"
      ]
    },
    {
      "d": "2022-07-18",
      "ix": "A086880(n)-A000188(A153197(n))",
      "mt": 8,
      "px": [
        "n",
        "A086880",
        "n",
        "A153197",
        "A000188",
        "sub"
      ]
    }
  ]
}