{
  "oi": 106690,
  "ps": [
    {
      "d": "2021-11-24",
      "ix": "A111312(n+1)+9",
      "mt": 10000,
      "px": [
        "n",
        "1",
        "+",
        "A111312",
        "9",
        "+"
      ]
    },
    {
      "d": "2021-12-30",
      "ix": "ceil(p?[a(n-1)+11]/11)+8",
      "mt": 7843,
      "px": [
        "6",
        "2",
        "n",
        "1",
        "sub",
        "a",
        "11",
        "+",
        "p?",
        "11",
        "/",
        "ceil",
        "8",
        "+"
      ]
    },
    {
      "d": "2021-12-30",
      "ix": "round(p?[a(n-1)+11]/11)+9",
      "mt": 7843,
      "px": [
        "10",
        "2",
        "n",
        "1",
        "sub",
        "a",
        "11",
        "+",
        "p?",
        "11",
        "/",
        "round",
        "9",
        "+"
      ]
    },
    {
      "d": "2021-11-26",
      "ix": "eq[2, A000005(11*n+2)]+9",
      "mt": 1816,
      "px": [
        "2",
        "11",
        "n",
        "*",
        "2",
        "+",
        "A000005",
        "eq",
        "9",
        "+"
      ]
    },
    {
      "d": "2022-04-05",
      "ix": "record[(n+9)/A001222(A017425(n)-1)]",
      "mt": 1047,
      "px": [
        "n",
        "9",
        "+",
        "n",
        "A017425",
        "1",
        "sub",
        "A001222",
        "/",
        "record"
      ]
    },
    {
      "d": "2021-12-23",
      "ix": "A020723(A111312(n+1))",
      "mt": 1047,
      "px": [
        "n",
        "1",
        "+",
        "A111312",
        "A020723"
      ]
    },
    {
      "d": "2022-02-23",
      "ix": "A262115(p?[A017413(n)])+9",
      "mt": 120,
      "px": [
        "n",
        "A017413",
        "p?",
        "A262115",
        "9",
        "+"
      ]
    },
    {
      "d": "2021-11-24",
      "ix": "A262115(A090187(n+1))+9",
      "mt": 120,
      "px": [
        "n",
        "1",
        "+",
        "A090187",
        "A262115",
        "9",
        "+"
      ]
    }
  ]
}