{
  "oi": 171364,
  "ps": [
    {
      "d": "2022-07-04",
      "ix": "A171307(eq[29, A066657(n)])",
      "mt": 8,
      "px": [
        "29",
        "n",
        "A066657",
        "eq",
        "A171307"
      ]
    },
    {
      "d": "2023-06-11",
      "ix": "A171307(A000217(n+12)+13)",
      "mt": 8,
      "px": [
        "n",
        "12",
        "+",
        "A000217",
        "13",
        "+",
        "A171307"
      ]
    },
    {
      "d": "2022-06-19",
      "ix": "A171307(eq[14, A131818(n+1)])",
      "mt": 8,
      "px": [
        "14",
        "n",
        "1",
        "+",
        "A131818",
        "eq",
        "A171307"
      ]
    }
  ]
}