{
  "oi": 368998,
  "ps": [
    {
      "d": "2024-02-03",
      "ix": "eq[1, A368997(n+1)]+1",
      "mt": 10000,
      "px": [
        "1",
        "n",
        "1",
        "+",
        "A368997",
        "eq",
        "1",
        "+"
      ]
    },
    {
      "d": "2024-01-31",
      "ix": "∪[A046337(n+1), A108269(n+1)]",
      "mt": 10000,
      "px": [
        "n",
        "1",
        "+",
        "A046337",
        "n",
        "1",
        "+",
        "A108269",
        "∪"
      ]
    },
    {
      "d": "2024-01-31",
      "ix": "∪[A108269(n+1), A369002(n+1)]",
      "mt": 10000,
      "px": [
        "n",
        "1",
        "+",
        "A108269",
        "n",
        "1",
        "+",
        "A369002",
        "∪"
      ]
    },
    {
      "d": "2024-02-01",
      "ix": "∩[A003159(n+1), A235992(n+1)]",
      "mt": 6182,
      "px": [
        "n",
        "1",
        "+",
        "A003159",
        "n",
        "1",
        "+",
        "A235992",
        "∩"
      ]
    }
  ]
}