{
  "oi": 231637,
  "ps": [
    {
      "d": "2022-06-25",
      "ix": "A231641(∑[n+2]+4)",
      "mt": 11,
      "px": [
        "n",
        "2",
        "+",
        "∑",
        "4",
        "+",
        "A231641"
      ]
    },
    {
      "d": "2022-07-04",
      "ix": "or(floor(acot(n)), A231641(A167614(n+1)))",
      "mt": 11,
      "px": [
        "n",
        "acot",
        "floor",
        "n",
        "1",
        "+",
        "A167614",
        "A231641",
        "or"
      ]
    },
    {
      "d": "2025-06-13",
      "ix": "record[root(A231641(n+4), A049834(n+1))]",
      "mt": 11,
      "px": [
        "n",
        "4",
        "+",
        "A231641",
        "n",
        "1",
        "+",
        "A049834",
        "root",
        "record"
      ]
    },
    {
      "d": "2022-07-04",
      "ix": "record[A231641(A167614(∑{e}[n+1, #]+1))]",
      "mt": 11,
      "px": [
        "n",
        "1",
        "+",
        "#",
        "∑{e}",
        "1",
        "+",
        "A167614",
        "A231641",
        "record"
      ]
    },
    {
      "d": "2022-07-04",
      "ix": "A231641(A167614(n+1))+A011744(n)",
      "mt": 11,
      "px": [
        "n",
        "1",
        "+",
        "A167614",
        "A231641",
        "n",
        "A011744",
        "+"
      ]
    }
  ]
}