{
  "oi": 168969,
  "ps": [
    {
      "d": "2022-06-06",
      "ix": "3*(a(n-1)-A004198(A185044(n)))",
      "mt": 24,
      "px": [
        "1",
        "4",
        "3",
        "n",
        "1",
        "sub",
        "a",
        "n",
        "A185044",
        "A004198",
        "sub",
        "*"
      ]
    },
    {
      "d": "2022-05-29",
      "ix": "3*(a(n-1)-A309785(A331562(n)))",
      "mt": 24,
      "px": [
        "1",
        "4",
        "3",
        "n",
        "1",
        "sub",
        "a",
        "n",
        "A331562",
        "A309785",
        "sub",
        "*"
      ]
    },
    {
      "d": "2023-09-04",
      "ix": "A003946(n)-A241065(A034432(2*n+2))",
      "mt": 24,
      "px": [
        "n",
        "A003946",
        "2",
        "n",
        "*",
        "2",
        "+",
        "A034432",
        "A241065",
        "sub"
      ]
    },
    {
      "d": "2023-09-04",
      "ix": "∑[A080923(n)]-A241065(A034432(2*n+2))",
      "mt": 24,
      "px": [
        "n",
        "A080923",
        "∑",
        "2",
        "n",
        "*",
        "2",
        "+",
        "A034432",
        "A241065",
        "sub"
      ]
    },
    {
      "d": "2023-09-04",
      "ix": "A326339(n+2)-A241065(A034432(2*n+2))",
      "mt": 24,
      "px": [
        "n",
        "2",
        "+",
        "A326339",
        "2",
        "n",
        "*",
        "2",
        "+",
        "A034432",
        "A241065",
        "sub"
      ]
    }
  ]
}