{
  "oi": 365208,
  "ps": [
    {
      "d": "2024-09-15",
      "ix": "∑{d}[n+1, A072078(#)*A373154((n+1)/#)]",
      "mt": 10000,
      "px": [
        "n",
        "1",
        "+",
        "#",
        "A072078",
        "n",
        "1",
        "+",
        "#",
        "/",
        "A373154",
        "*",
        "∑{d}"
      ]
    },
    {
      "d": "2024-12-14",
      "ix": "A000005(lcm(gcd(n+1, (n+13)^9), A007947(n+1)))",
      "mt": 10000,
      "px": [
        "n",
        "1",
        "+",
        "n",
        "13",
        "+",
        "9",
        "^",
        "gcd",
        "n",
        "1",
        "+",
        "A007947",
        "lcm",
        "A000005"
      ]
    },
    {
      "d": "2025-03-31",
      "ix": "A000005(n+1)-A010815(A080386(n+2))",
      "mt": 48,
      "px": [
        "n",
        "1",
        "+",
        "A000005",
        "n",
        "2",
        "+",
        "A080386",
        "A010815",
        "sub"
      ]
    },
    {
      "d": "2025-04-02",
      "ix": "A000005(A284011(n+1)%A000043(n+1))",
      "mt": 48,
      "px": [
        "n",
        "1",
        "+",
        "A284011",
        "n",
        "1",
        "+",
        "A000043",
        "%",
        "A000005"
      ]
    },
    {
      "d": "2025-03-31",
      "ix": "A000005(n+1)-A378537(A000041(n))",
      "mt": 47,
      "px": [
        "n",
        "1",
        "+",
        "A000005",
        "n",
        "A000041",
        "A378537",
        "sub"
      ]
    }
  ]
}