{
  "oi": 5911,
  "ps": [
    {
      "d": "2022-04-08",
      "ix": "round(3/acot(n)²)+43*n²",
      "mt": 10000,
      "px": [
        "3",
        "n",
        "acot",
        "²",
        "/",
        "round",
        "43",
        "n",
        "²",
        "*",
        "+"
      ]
    },
    {
      "d": "2023-07-01",
      "ix": "21*n²+Δ[floor((2*n)²/(2*n+1))^3]+n²",
      "mt": 10000,
      "px": [
        "21",
        "n",
        "²",
        "*",
        "2",
        "n",
        "*",
        "²",
        "2",
        "n",
        "*",
        "1",
        "+",
        "/",
        "floor",
        "3",
        "^",
        "Δ",
        "n",
        "²",
        "+",
        "+"
      ]
    },
    {
      "d": "2023-07-08",
      "ix": "A000027(A158632(n)%A098262(n)+1)",
      "mt": 36,
      "px": [
        "n",
        "A158632",
        "n",
        "A098262",
        "%",
        "1",
        "+",
        "A000027"
      ]
    },
    {
      "d": "2023-07-08",
      "ix": "A103517(23*n²)",
      "mt": 21,
      "px": [
        "23",
        "n",
        "²",
        "*",
        "A103517"
      ]
    },
    {
      "d": "2023-07-06",
      "ix": "A335024(46*n²+1)",
      "mt": 21,
      "px": [
        "46",
        "n",
        "²",
        "*",
        "1",
        "+",
        "A335024"
      ]
    }
  ]
}