{
  "oi": 324293,
  "ps": [
    {
      "d": "2021-11-01",
      "ix": "A002487(A000203(n+1))",
      "mt": 3119,
      "px": [
        "n",
        "1",
        "+",
        "A000203",
        "A002487"
      ],
      "tags": [
        "proven"
      ]
    },
    {
      "d": "2021-11-24",
      "ix": "A002487(A161942(n+1))",
      "mt": 3527,
      "px": [
        "n",
        "1",
        "+",
        "A161942",
        "A002487"
      ]
    },
    {
      "d": "2021-11-01",
      "ix": "A002487(∑{d}[n+1, #])",
      "mt": 3119,
      "px": [
        "n",
        "1",
        "+",
        "#",
        "∑{d}",
        "A002487"
      ]
    },
    {
      "d": "2023-07-02",
      "ix": "A002487(Δ[A160664(n)])",
      "mt": 3119,
      "px": [
        "n",
        "A160664",
        "Δ",
        "A002487"
      ]
    },
    {
      "d": "2023-06-22",
      "ix": "A002487(abs(Δ[A330725(n)]))",
      "mt": 3119,
      "px": [
        "n",
        "A330725",
        "Δ",
        "abs",
        "A002487"
      ]
    },
    {
      "d": "2023-06-20",
      "ix": "A002487(A245092(Δ[n²]))",
      "mt": 3119,
      "px": [
        "n",
        "²",
        "Δ",
        "A245092",
        "A002487"
      ]
    },
    {
      "d": "2023-06-21",
      "ix": "A002487(∑[A340793(n+1)])",
      "mt": 3119,
      "px": [
        "n",
        "1",
        "+",
        "A340793",
        "∑",
        "A002487"
      ]
    },
    {
      "d": "2021-11-24",
      "ix": "A002487(A088580(n+1)-1)",
      "mt": 3119,
      "px": [
        "n",
        "1",
        "+",
        "A088580",
        "1",
        "sub",
        "A002487"
      ]
    },
    {
      "d": "2021-12-06",
      "ix": "A002487(A074400(n+1)/2)",
      "mt": 3119,
      "px": [
        "n",
        "1",
        "+",
        "A074400",
        "2",
        "/",
        "A002487"
      ]
    },
    {
      "d": "2022-10-07",
      "ix": "A002487(A001065(n+1)+1+n)",
      "mt": 3119,
      "px": [
        "n",
        "1",
        "+",
        "A001065",
        "1",
        "+",
        "n",
        "+",
        "A002487"
      ]
    },
    {
      "d": "2024-09-16",
      "ix": "A002487(A048050(n+1)+n+2)",
      "mt": 3119,
      "px": [
        "n",
        "1",
        "+",
        "A048050",
        "n",
        "2",
        "+",
        "+",
        "A002487"
      ]
    },
    {
      "d": "2022-10-07",
      "ix": "A002487(A155085(n+1)-(n+1))",
      "mt": 3119,
      "px": [
        "n",
        "1",
        "+",
        "A155085",
        "n",
        "1",
        "+",
        "sub",
        "A002487"
      ]
    },
    {
      "d": "2022-10-07",
      "ix": "A002487(A064987(n+1)/(n+1))",
      "mt": 3119,
      "px": [
        "n",
        "1",
        "+",
        "A064987",
        "n",
        "1",
        "+",
        "/",
        "A002487"
      ]
    },
    {
      "d": "2022-10-07",
      "ix": "A002487(A237588(n+1)+Δ[n²])",
      "mt": 3119,
      "px": [
        "n",
        "1",
        "+",
        "A237588",
        "n",
        "²",
        "Δ",
        "+",
        "A002487"
      ]
    },
    {
      "d": "2022-10-07",
      "ix": "A002487(A070039(n+1)+A070038(n+1))",
      "mt": 3119,
      "px": [
        "n",
        "1",
        "+",
        "A070039",
        "n",
        "1",
        "+",
        "A070038",
        "+",
        "A002487"
      ]
    },
    {
      "d": "2021-11-24",
      "ix": "A317840(2*A000203(n+1))",
      "mt": 2519,
      "px": [
        "2",
        "n",
        "1",
        "+",
        "A000203",
        "*",
        "A317840"
      ]
    },
    {
      "d": "2021-11-24",
      "ix": "A002487(A074400(n+1))",
      "mt": 1559,
      "px": [
        "n",
        "1",
        "+",
        "A074400",
        "A002487"
      ]
    },
    {
      "d": "2021-11-24",
      "ix": "A288003(A002659(n+1))",
      "mt": 1559,
      "px": [
        "n",
        "1",
        "+",
        "A002659",
        "A288003"
      ]
    },
    {
      "d": "2021-11-01",
      "ix": "A295515(2*A000203(n+1))",
      "mt": 1559,
      "px": [
        "2",
        "n",
        "1",
        "+",
        "A000203",
        "*",
        "A295515"
      ]
    }
  ]
}