{
  "oi": 132753,
  "ps": [
    {
      "d": "2025-04-20",
      "ix": "4*a(n-1)-5*a(n-2)+2*a(n-3)",
      "mt": 331,
      "px": [
        "3",
        "4",
        "7",
        "4",
        "n",
        "1",
        "sub",
        "a",
        "*",
        "5",
        "n",
        "2",
        "sub",
        "a",
        "*",
        "sub",
        "2",
        "n",
        "3",
        "sub",
        "a",
        "*",
        "+"
      ],
      "s": "oeis",
      "tags": [
        "proven"
      ]
    },
    {
      "d": "2021-11-01",
      "ix": "∑[2^n-1]+3",
      "mt": 332,
      "px": [
        "2",
        "n",
        "^",
        "1",
        "sub",
        "∑",
        "3",
        "+"
      ]
    },
    {
      "d": "2021-11-01",
      "ix": "record[or(2, 2^n)-n]",
      "mt": 332,
      "px": [
        "2",
        "2",
        "n",
        "^",
        "or",
        "n",
        "sub",
        "record"
      ]
    },
    {
      "d": "2021-11-01",
      "ix": "record[xor(2, 2^n)-n]",
      "mt": 332,
      "px": [
        "2",
        "2",
        "n",
        "^",
        "xor",
        "n",
        "sub",
        "record"
      ]
    },
    {
      "d": "2022-08-31",
      "ix": "∑[ogf((3-8x+6x^2)/(1-3x+2x^2))]",
      "mt": 332,
      "px": [
        "3",
        "1",
        "-3",
        "2",
        "3",
        "-8",
        "6",
        "ogf",
        "∑"
      ]
    },
    {
      "d": "2022-08-31",
      "ix": "ogf((3-8x+6x^2)/(1-4x+5x^2-2x^3))",
      "mt": 332,
      "px": [
        "4",
        "1",
        "-4",
        "5",
        "-2",
        "3",
        "-8",
        "6",
        "ogf"
      ]
    },
    {
      "d": "2022-05-14",
      "ix": "abs(or(1, 2^(n+1))-n)",
      "mt": 332,
      "px": [
        "1",
        "2",
        "n",
        "1",
        "+",
        "^",
        "or",
        "n",
        "sub",
        "abs"
      ]
    },
    {
      "d": "2022-05-14",
      "ix": "abs(xor(1, 2^(n+1))-n)",
      "mt": 332,
      "px": [
        "1",
        "2",
        "n",
        "1",
        "+",
        "^",
        "xor",
        "n",
        "sub",
        "abs"
      ]
    },
    {
      "d": "2021-11-06",
      "ix": "∑[2*a(n-1)+1]",
      "mt": 332,
      "px": [
        "3",
        "1",
        "2",
        "n",
        "1",
        "sub",
        "a",
        "*",
        "1",
        "+",
        "∑"
      ]
    },
    {
      "d": "2022-07-19",
      "ix": "∑[lcm(2, a(n-1))+1]",
      "mt": 332,
      "px": [
        "3",
        "1",
        "2",
        "n",
        "1",
        "sub",
        "a",
        "lcm",
        "1",
        "+",
        "∑"
      ]
    },
    {
      "d": "2022-07-19",
      "ix": "∑[or(1, 2*a(n-1))]",
      "mt": 332,
      "px": [
        "3",
        "1",
        "1",
        "2",
        "n",
        "1",
        "sub",
        "a",
        "*",
        "or",
        "∑"
      ]
    },
    {
      "d": "2022-07-19",
      "ix": "∑[xor(1, 2*a(n-1))]",
      "mt": 332,
      "px": [
        "3",
        "1",
        "1",
        "2",
        "n",
        "1",
        "sub",
        "a",
        "*",
        "xor",
        "∑"
      ]
    },
    {
      "d": "2022-06-24",
      "ix": "floor(record[2^(n-1)-(n-3)])",
      "mt": 332,
      "px": [
        "2",
        "n",
        "1",
        "sub",
        "^",
        "n",
        "3",
        "sub",
        "sub",
        "record",
        "floor"
      ]
    },
    {
      "d": "2022-09-23",
      "ix": "∑[∑[2*a(n-1)]]",
      "mt": 332,
      "px": [
        "3",
        "-2",
        "2",
        "2",
        "n",
        "1",
        "sub",
        "a",
        "*",
        "∑",
        "∑"
      ]
    },
    {
      "d": "2022-06-24",
      "ix": "xor(n-2-2^(n+1), -1)",
      "mt": 332,
      "px": [
        "n",
        "2",
        "sub",
        "2",
        "n",
        "1",
        "+",
        "^",
        "sub",
        "1",
        "neg",
        "xor"
      ]
    },
    {
      "d": "2022-07-15",
      "ix": "floor(2*a(n-1)-3+n)",
      "mt": 332,
      "px": [
        "3",
        "2",
        "n",
        "1",
        "sub",
        "a",
        "*",
        "3",
        "sub",
        "n",
        "+",
        "floor"
      ]
    },
    {
      "d": "2022-07-15",
      "ix": "floor(2*a(n-1)-(3-n))",
      "mt": 332,
      "px": [
        "3",
        "2",
        "n",
        "1",
        "sub",
        "a",
        "*",
        "3",
        "n",
        "sub",
        "sub",
        "floor"
      ]
    },
    {
      "d": "2022-05-29",
      "ix": "floor(2^n+a(n-1)-1)",
      "mt": 332,
      "px": [
        "3",
        "2",
        "n",
        "^",
        "n",
        "1",
        "sub",
        "a",
        "1",
        "sub",
        "+",
        "floor"
      ]
    },
    {
      "d": "2022-05-29",
      "ix": "floor(2^n-(1-a(n-1)))",
      "mt": 332,
      "px": [
        "3",
        "2",
        "n",
        "^",
        "1",
        "n",
        "1",
        "sub",
        "a",
        "sub",
        "sub",
        "floor"
      ]
    },
    {
      "d": "2022-10-19",
      "ix": "abs(2^C(n+1, n)-(n-1))",
      "mt": 332,
      "px": [
        "2",
        "n",
        "1",
        "+",
        "n",
        "C",
        "^",
        "n",
        "1",
        "sub",
        "sub",
        "abs"
      ]
    }
  ]
}