{
  "oi": 77912,
  "ps": [
    {
      "d": "2022-08-31",
      "ix": "ogf(1/(1+x^2-2x^3))",
      "mt": 667,
      "px": [
        "4",
        "1",
        "0",
        "1",
        "-2",
        "1",
        "ogf"
      ]
    },
    {
      "d": "2022-09-23",
      "ix": "2*a(n-3)-a(n-2)",
      "mt": 667,
      "px": [
        "1",
        "0",
        "-1",
        "2",
        "n",
        "3",
        "sub",
        "a",
        "*",
        "n",
        "2",
        "sub",
        "a",
        "sub"
      ]
    },
    {
      "d": "2022-09-23",
      "ix": "a(n-3)+a(n-3)-a(n-2)",
      "mt": 667,
      "px": [
        "1",
        "0",
        "-1",
        "n",
        "3",
        "sub",
        "a",
        "n",
        "3",
        "sub",
        "a",
        "n",
        "2",
        "sub",
        "a",
        "sub",
        "+"
      ]
    },
    {
      "d": "2021-11-06",
      "ix": "1-a(n-1)-a(n-2)-a(n-2)",
      "mt": 667,
      "px": [
        "1",
        "0",
        "1",
        "n",
        "1",
        "sub",
        "a",
        "sub",
        "n",
        "2",
        "sub",
        "a",
        "sub",
        "n",
        "2",
        "sub",
        "a",
        "sub"
      ]
    },
    {
      "d": "2025-04-12",
      "ix": "(-1)^n*A077963(n)",
      "mt": 667,
      "px": [
        "1",
        "neg",
        "n",
        "^",
        "n",
        "A077963",
        "*"
      ],
      "s": "oeis",
      "tags": [
        "proven"
      ]
    },
    {
      "d": "2022-07-17",
      "ix": "A110512(n)+a(n-2)",
      "mt": 665,
      "px": [
        "1",
        "0",
        "n",
        "A110512",
        "n",
        "2",
        "sub",
        "a",
        "+"
      ]
    },
    {
      "d": "2021-10-01",
      "ix": "∑[A110512(n)-A001607(n)]",
      "mt": 663,
      "px": [
        "n",
        "A110512",
        "n",
        "A001607",
        "sub",
        "∑"
      ]
    },
    {
      "d": "2021-10-01",
      "ix": "Δ[A077887(A130716(n+2)+abs(1-n))]",
      "mt": 663,
      "px": [
        "n",
        "2",
        "+",
        "A130716",
        "1",
        "n",
        "sub",
        "abs",
        "+",
        "A077887",
        "Δ"
      ]
    },
    {
      "d": "2021-11-01",
      "ix": "∑[A001607(n+1)]",
      "mt": 662,
      "px": [
        "n",
        "1",
        "+",
        "A001607",
        "∑"
      ]
    },
    {
      "d": "2022-06-25",
      "ix": "a(n-1)-A169998(n-1)",
      "mt": 661,
      "px": [
        "1",
        "n",
        "1",
        "sub",
        "a",
        "n",
        "1",
        "sub",
        "A169998",
        "sub"
      ]
    },
    {
      "d": "2021-11-01",
      "ix": "∑[∑[A078050(n)]]",
      "mt": 659,
      "px": [
        "n",
        "A078050",
        "∑",
        "∑"
      ]
    },
    {
      "d": "2021-10-01",
      "ix": "ceil(A001607(n+4)/4)",
      "mt": 659,
      "px": [
        "n",
        "4",
        "+",
        "A001607",
        "4",
        "/",
        "ceil"
      ]
    },
    {
      "d": "2021-12-30",
      "ix": "2*A089977(n)-∑[A089977(n)]",
      "mt": 333,
      "px": [
        "2",
        "n",
        "A089977",
        "*",
        "n",
        "A089977",
        "∑",
        "sub"
      ]
    }
  ]
}