{
  "oi": 34550,
  "ps": [
    {
      "d": "2021-11-24",
      "ix": "A163874(A034564(n+2))",
      "mt": 32,
      "px": [
        "n",
        "2",
        "+",
        "A034564",
        "A163874"
      ]
    },
    {
      "d": "2021-11-24",
      "ix": "A165565(A034529(n+2))",
      "mt": 32,
      "px": [
        "n",
        "2",
        "+",
        "A034529",
        "A165565"
      ]
    },
    {
      "d": "2021-11-24",
      "ix": "A329200(A034538(n+2))",
      "mt": 32,
      "px": [
        "n",
        "2",
        "+",
        "A034538",
        "A329200"
      ]
    },
    {
      "d": "2021-11-24",
      "ix": "A329200(A034540(n+2))",
      "mt": 32,
      "px": [
        "n",
        "2",
        "+",
        "A034540",
        "A329200"
      ]
    },
    {
      "d": "2022-10-06",
      "ix": "A111660(2*A034538(n+2))",
      "mt": 32,
      "px": [
        "2",
        "n",
        "2",
        "+",
        "A034538",
        "*",
        "A111660"
      ]
    }
  ]
}