{
  "oi": 71317,
  "ps": [
    {
      "d": "2021-11-01",
      "ix": "∑[∑{digits}[n², #]]",
      "mt": 10000,
      "px": [
        "n",
        "²",
        "#",
        "∑{digits}",
        "∑"
      ]
    },
    {
      "d": "2021-11-01",
      "ix": "∑[log2(∏{digits}[n², 2^#])]",
      "mt": 10000,
      "px": [
        "n",
        "²",
        "2",
        "#",
        "^",
        "∏{digits}",
        "log2",
        "∑"
      ]
    },
    {
      "d": "2021-11-06",
      "ix": "∑{digits}[n², #]+a(n-1)",
      "mt": 10000,
      "px": [
        "0",
        "n",
        "²",
        "#",
        "∑{digits}",
        "n",
        "1",
        "sub",
        "a",
        "+"
      ]
    },
    {
      "d": "2021-11-01",
      "ix": "∑[A004159(n)]",
      "mt": 10000,
      "px": [
        "n",
        "A004159",
        "∑"
      ]
    },
    {
      "d": "2021-11-01",
      "ix": "∑[n²-A224977(n)]",
      "mt": 10000,
      "px": [
        "n",
        "²",
        "n",
        "A224977",
        "sub",
        "∑"
      ]
    },
    {
      "d": "2021-12-30",
      "ix": "∑[∑[A240752(n+1)]-A240752(n+1)]",
      "mt": 10000,
      "px": [
        "n",
        "1",
        "+",
        "A240752",
        "∑",
        "n",
        "1",
        "+",
        "A240752",
        "sub",
        "∑"
      ]
    },
    {
      "d": "2021-11-01",
      "ix": "∑[A268227(5*n)]",
      "mt": 2000,
      "px": [
        "5",
        "n",
        "*",
        "A268227",
        "∑"
      ]
    },
    {
      "d": "2021-11-01",
      "ix": "∑[A007953(n²)]",
      "mt": 101,
      "px": [
        "n",
        "²",
        "A007953",
        "∑"
      ]
    },
    {
      "d": "2021-12-06",
      "ix": "∑[sqrt(A118881(n²))]",
      "mt": 101,
      "px": [
        "n",
        "²",
        "A118881",
        "sqrt",
        "∑"
      ]
    },
    {
      "d": "2021-12-06",
      "ix": "∑[log2(A329562(n²))]",
      "mt": 101,
      "px": [
        "n",
        "²",
        "A329562",
        "log2",
        "∑"
      ]
    },
    {
      "d": "2022-07-17",
      "ix": "A007953(n*n)+a(n-1)",
      "mt": 101,
      "px": [
        "0",
        "n",
        "n",
        "*",
        "A007953",
        "n",
        "1",
        "sub",
        "a",
        "+"
      ]
    },
    {
      "d": "2021-11-01",
      "ix": "∑[A169805(n²)/2]",
      "mt": 100,
      "px": [
        "n",
        "²",
        "A169805",
        "2",
        "/",
        "∑"
      ]
    },
    {
      "d": "2021-10-01",
      "ix": "A006370(∑[A169805(n²)])",
      "mt": 100,
      "px": [
        "n",
        "²",
        "A169805",
        "∑",
        "A006370"
      ]
    }
  ]
}