{
  "oi": 370078,
  "ps": [
    {
      "d": "2024-05-13",
      "ix": "log2(A370077(n+1))",
      "mt": 10000,
      "px": [
        "n",
        "1",
        "+",
        "A370077",
        "log2"
      ]
    },
    {
      "d": "2024-12-13",
      "ix": "A145037(A370077(n+1)-1)",
      "mt": 10000,
      "px": [
        "n",
        "1",
        "+",
        "A370077",
        "1",
        "sub",
        "A145037"
      ]
    },
    {
      "d": "2025-03-28",
      "ix": "A334201(2*A370077(n+1))",
      "mt": 10000,
      "px": [
        "2",
        "n",
        "1",
        "+",
        "A370077",
        "*",
        "A334201"
      ]
    },
    {
      "d": "2024-12-12",
      "ix": "∑{e}[n+1, A007814(A100994(#))]",
      "mt": 10000,
      "px": [
        "n",
        "1",
        "+",
        "#",
        "A100994",
        "A007814",
        "∑{e}"
      ]
    },
    {
      "d": "2024-12-12",
      "ix": "A056239(A370077(n+1)%A000040(n+1))",
      "mt": 10000,
      "px": [
        "n",
        "1",
        "+",
        "A370077",
        "n",
        "1",
        "+",
        "A000040",
        "%",
        "A056239"
      ]
    },
    {
      "d": "2024-12-08",
      "ix": "A367169(A367170(A350388(n+1)²))",
      "mt": 120,
      "px": [
        "n",
        "1",
        "+",
        "A350388",
        "²",
        "A367170",
        "A367169"
      ]
    },
    {
      "d": "2024-05-13",
      "ix": "A087476(A066060(n+1))",
      "mt": 63,
      "px": [
        "n",
        "1",
        "+",
        "A066060",
        "A087476"
      ]
    },
    {
      "d": "2025-03-23",
      "ix": "A074970(A112624(n+1))",
      "mt": 63,
      "px": [
        "n",
        "1",
        "+",
        "A112624",
        "A074970"
      ]
    },
    {
      "d": "2024-09-18",
      "ix": "A238877(A066060(n+1)²+1)",
      "mt": 63,
      "px": [
        "n",
        "1",
        "+",
        "A066060",
        "²",
        "1",
        "+",
        "A238877"
      ]
    },
    {
      "d": "2024-12-12",
      "ix": "A007814(A005361(n+1)*A006512(n+1))",
      "mt": 63,
      "px": [
        "n",
        "1",
        "+",
        "A005361",
        "n",
        "1",
        "+",
        "A006512",
        "*",
        "A007814"
      ]
    }
  ]
}