{
  "oi": 70049,
  "ps": [
    {
      "d": "2024-05-15",
      "ix": "∪[A068537(n+1), A298591(n+1)]",
      "mt": 10000,
      "px": [
        "n",
        "1",
        "+",
        "A068537",
        "n",
        "1",
        "+",
        "A298591",
        "∪"
      ]
    },
    {
      "d": "2024-05-15",
      "ix": "eq[A000038(n)², A000038(A362426(n))]",
      "mt": 4138,
      "px": [
        "n",
        "A000038",
        "²",
        "n",
        "A362426",
        "A000038",
        "eq"
      ]
    },
    {
      "d": "2023-03-04",
      "ix": "∩[A076871(n+1), A327609(n+1)]",
      "mt": 64,
      "px": [
        "n",
        "1",
        "+",
        "A076871",
        "n",
        "1",
        "+",
        "A327609",
        "∩"
      ]
    },
    {
      "d": "2022-07-15",
      "ix": "record[A076871(n+1)%A195927(n+1)]",
      "mt": 54,
      "px": [
        "n",
        "1",
        "+",
        "A076871",
        "n",
        "1",
        "+",
        "A195927",
        "%",
        "record"
      ]
    }
  ]
}