{
  "oi": 376337,
  "ps": [
    {
      "d": "2024-12-07",
      "ix": "or(1, A191611(n+1))",
      "mt": 9,
      "px": [
        "1",
        "n",
        "1",
        "+",
        "A191611",
        "or"
      ]
    },
    {
      "d": "2025-03-30",
      "ix": "record[A332212(2*n+3)]",
      "mt": 9,
      "px": [
        "2",
        "n",
        "*",
        "3",
        "+",
        "A332212",
        "record"
      ]
    },
    {
      "d": "2025-04-19",
      "ix": "record[A212953(A051377(n+2))]",
      "mt": 9,
      "px": [
        "n",
        "2",
        "+",
        "A051377",
        "A212953",
        "record"
      ]
    },
    {
      "d": "2026-04-15",
      "ix": "∩[A070763(n+1), A209492(n)]",
      "mt": 9,
      "px": [
        "n",
        "1",
        "+",
        "A070763",
        "n",
        "A209492",
        "∩"
      ]
    },
    {
      "d": "2026-04-15",
      "ix": "∩[A071114(n+1), A209492(n)]",
      "mt": 9,
      "px": [
        "n",
        "1",
        "+",
        "A071114",
        "n",
        "A209492",
        "∩"
      ]
    }
  ]
}