{
  "oi": 63016,
  "ps": [
    {
      "d": "2022-12-27",
      "ix": "A000108(n)*A126646(n)",
      "mt": 115,
      "px": [
        "n",
        "A000108",
        "n",
        "A126646",
        "*"
      ],
      "tags": [
        "proven"
      ]
    },
    {
      "d": "2023-05-22",
      "ix": "C(2*n, n)/(n+1)*2^n+(4-6/(n+1))*a(n-1)",
      "mt": 115,
      "px": [
        "1",
        "2",
        "n",
        "*",
        "n",
        "C",
        "n",
        "1",
        "+",
        "/",
        "2",
        "n",
        "^",
        "*",
        "4",
        "6",
        "n",
        "1",
        "+",
        "/",
        "sub",
        "n",
        "1",
        "sub",
        "a",
        "*",
        "+"
      ]
    },
    {
      "d": "2022-07-28",
      "ix": "abs(A168491(n))*∑[2^n]",
      "mt": 115,
      "px": [
        "n",
        "A168491",
        "abs",
        "2",
        "n",
        "^",
        "∑",
        "*"
      ]
    },
    {
      "d": "2022-07-24",
      "ix": "∑[2^n]*A120588(n+1)",
      "mt": 115,
      "px": [
        "2",
        "n",
        "^",
        "∑",
        "n",
        "1",
        "+",
        "A120588",
        "*"
      ]
    },
    {
      "d": "2022-07-24",
      "ix": "(A120304(n)+2)*∑[2^n]",
      "mt": 115,
      "px": [
        "n",
        "A120304",
        "2",
        "+",
        "2",
        "n",
        "^",
        "∑",
        "*"
      ]
    },
    {
      "d": "2022-07-24",
      "ix": "∑[2^n]*A028304(2*n)",
      "mt": 115,
      "px": [
        "2",
        "n",
        "^",
        "∑",
        "2",
        "n",
        "*",
        "A028304",
        "*"
      ]
    },
    {
      "d": "2022-07-24",
      "ix": "∑[2^n]*A208355(2*n)",
      "mt": 115,
      "px": [
        "2",
        "n",
        "^",
        "∑",
        "2",
        "n",
        "*",
        "A208355",
        "*"
      ]
    },
    {
      "d": "2022-07-24",
      "ix": "abs(A115140(n+1))*∑[2^n]",
      "mt": 115,
      "px": [
        "n",
        "1",
        "+",
        "A115140",
        "abs",
        "2",
        "n",
        "^",
        "∑",
        "*"
      ]
    },
    {
      "d": "2022-07-24",
      "ix": "∑[2^n]*Δ[A166588(2*n)]",
      "mt": 115,
      "px": [
        "2",
        "n",
        "^",
        "∑",
        "2",
        "n",
        "*",
        "A166588",
        "Δ",
        "*"
      ]
    },
    {
      "d": "2022-02-09",
      "ix": "record[A052551(n)*A097331(n)]",
      "mt": 115,
      "px": [
        "n",
        "A052551",
        "n",
        "A097331",
        "*",
        "record"
      ]
    },
    {
      "d": "2022-01-27",
      "ix": "record[A052955(n)*A126120(n)]",
      "mt": 115,
      "px": [
        "n",
        "A052955",
        "n",
        "A126120",
        "*",
        "record"
      ]
    },
    {
      "d": "2021-12-23",
      "ix": "A025225(n+1)-A000108(n)",
      "mt": 115,
      "px": [
        "n",
        "1",
        "+",
        "A025225",
        "n",
        "A000108",
        "sub"
      ]
    },
    {
      "d": "2022-09-14",
      "ix": "A115125(n+1)-A000108(n)",
      "mt": 115,
      "px": [
        "n",
        "1",
        "+",
        "A115125",
        "n",
        "A000108",
        "sub"
      ]
    },
    {
      "d": "2022-12-26",
      "ix": "A000108(n)*A000225(n+1)",
      "mt": 115,
      "px": [
        "n",
        "A000108",
        "n",
        "1",
        "+",
        "A000225",
        "*"
      ]
    },
    {
      "d": "2022-10-07",
      "ix": "A120588(n+1)*A126646(n)",
      "mt": 115,
      "px": [
        "n",
        "1",
        "+",
        "A120588",
        "n",
        "A126646",
        "*"
      ]
    },
    {
      "d": "2022-10-06",
      "ix": "2*A151374(n)-A000108(n)",
      "mt": 115,
      "px": [
        "2",
        "n",
        "A151374",
        "*",
        "n",
        "A000108",
        "sub"
      ]
    },
    {
      "d": "2023-03-01",
      "ix": "A000108(n)*A086341(2*n)",
      "mt": 115,
      "px": [
        "n",
        "A000108",
        "2",
        "n",
        "*",
        "A086341",
        "*"
      ]
    },
    {
      "d": "2022-10-07",
      "ix": "A028303(2*n)*A126646(n)",
      "mt": 115,
      "px": [
        "2",
        "n",
        "*",
        "A028303",
        "n",
        "A126646",
        "*"
      ]
    },
    {
      "d": "2022-10-06",
      "ix": "abs(∑[A000079(n)]*A168491(n))",
      "mt": 115,
      "px": [
        "n",
        "A000079",
        "∑",
        "n",
        "A168491",
        "*",
        "abs"
      ]
    },
    {
      "d": "2025-04-14",
      "ix": "A000225(n+1)*A126120(2*n)",
      "mt": 115,
      "px": [
        "n",
        "1",
        "+",
        "A000225",
        "2",
        "n",
        "*",
        "A126120",
        "*"
      ]
    }
  ]
}