{
  "oi": 99452,
  "ps": [
    {
      "d": "2022-07-04",
      "ix": "record[A341221(n+3)-A001047(n)]",
      "mt": 6,
      "px": [
        "n",
        "3",
        "+",
        "A341221",
        "n",
        "A001047",
        "sub",
        "record"
      ]
    },
    {
      "d": "2022-06-27",
      "ix": "A302505(xor(A001844(n), A235938(n+1)))",
      "mt": 6,
      "px": [
        "n",
        "A001844",
        "n",
        "1",
        "+",
        "A235938",
        "xor",
        "A302505"
      ]
    }
  ]
}