{
  "oi": 272880,
  "ps": [
    {
      "d": "2021-11-24",
      "ix": "A067004(A272777(n+1))",
      "mt": 675,
      "px": [
        "n",
        "1",
        "+",
        "A272777",
        "A067004"
      ]
    },
    {
      "d": "2022-10-16",
      "ix": "A138009(A272777(gcd(n, 3*n-n)+1))",
      "mt": 675,
      "px": [
        "n",
        "3",
        "n",
        "*",
        "n",
        "sub",
        "gcd",
        "1",
        "+",
        "A272777",
        "A138009"
      ]
    },
    {
      "d": "2022-10-12",
      "ix": "A138009(A272777(n+1)%A002148(n))",
      "mt": 675,
      "px": [
        "n",
        "1",
        "+",
        "A272777",
        "n",
        "A002148",
        "%",
        "A138009"
      ]
    },
    {
      "d": "2022-10-12",
      "ix": "A138009(A272777(n+1))%A059154(n)",
      "mt": 675,
      "px": [
        "n",
        "1",
        "+",
        "A272777",
        "A138009",
        "n",
        "A059154",
        "%"
      ]
    },
    {
      "d": "2023-06-06",
      "ix": "A140225(A074929(n+1))",
      "mt": 16,
      "px": [
        "n",
        "1",
        "+",
        "A074929",
        "A140225"
      ]
    }
  ]
}