{
  "oi": 392725,
  "ps": [
    {
      "d": "2026-04-17",
      "ix": "A295931(A229096(n+1))-A309216(n)",
      "mt": 15,
      "px": [
        "n",
        "1",
        "+",
        "A229096",
        "A295931",
        "n",
        "A309216",
        "sub"
      ]
    },
    {
      "d": "2026-04-17",
      "ix": "A000035(A046006(2*n+5))-A309216(n)",
      "mt": 15,
      "px": [
        "2",
        "n",
        "*",
        "5",
        "+",
        "A046006",
        "A000035",
        "n",
        "A309216",
        "sub"
      ]
    },
    {
      "d": "2026-04-16",
      "ix": "A285384(A000079(n))-A309216(n)",
      "mt": 14,
      "px": [
        "n",
        "A000079",
        "A285384",
        "n",
        "A309216",
        "sub"
      ]
    },
    {
      "d": "2026-04-17",
      "ix": "A295931(A088172(n+1))-A309216(n)",
      "mt": 14,
      "px": [
        "n",
        "1",
        "+",
        "A088172",
        "A295931",
        "n",
        "A309216",
        "sub"
      ]
    },
    {
      "d": "2026-04-18",
      "ix": "A040001(A325067(3*(n+1)))-A309216(n)",
      "mt": 14,
      "px": [
        "3",
        "n",
        "1",
        "+",
        "*",
        "A325067",
        "A040001",
        "n",
        "A309216",
        "sub"
      ]
    }
  ]
}